telegram_notifier/__init__.py
telegram_notifier/__main__.py
telegram_notifier/config.py
telegram_notifier/notifier.py
py_telegram_notifier-1.0.0.dist-info/LICENSE
py_telegram_notifier-1.0.0.dist-info/METADATA
py_telegram_notifier-1.0.0.dist-info/WHEEL
py_telegram_notifier-1.0.0.dist-info/top_level.txt
py_telegram_notifier-1.0.0.dist-info/RECORD
