Metadata-Version: 2.1
Name: py_telegram_notifier
Version: 1.0.0
Summary: A tool using the Telegram Bot API for sending messages to a Telegram chat by a context manager, function call, or CLI.
Home-page: https://github.com/jon-edward/py-telegram-notifier
Author: Jonathan Townsend
Requires-Python: >=3.10
License-File: LICENSE
Requires-Dist: requests
